pytest_plt/__init__.py
pytest_plt/plugin.py
pytest_plt/version.py
pytest_plt/tests/__init__.py
pytest_plt/tests/test_plt.py
pytest_plt/tests/test_pytest.py
pytest_plt-1.1.1.dist-info/LICENSE.rst
pytest_plt-1.1.1.dist-info/METADATA
pytest_plt-1.1.1.dist-info/WHEEL
pytest_plt-1.1.1.dist-info/entry_points.txt
pytest_plt-1.1.1.dist-info/top_level.txt
pytest_plt-1.1.1.dist-info/RECORD
