Metadata-Version: 2.1
Name: pytest-plt
Version: 1.1.1
Summary: Fixtures for quickly making Matplotlib plots in tests
Home-page: https://www.nengo.ai/pytest-plt
Author: Applied Brain Research
Author-email: info@appliedbrainresearch.com
License: MIT license
Classifier: Development Status :: 5 - Production/Stable
Classifier: Framework :: Pytest
Classifier: License :: OSI Approved :: MIT License
Classifier: Programming Language :: Python :: 3 :: Only
Classifier: Programming Language :: Python :: 3.6
Classifier: Programming Language :: Python :: 3.7
Classifier: Programming Language :: Python :: 3.8
Classifier: Programming Language :: Python :: 3.9
Requires-Python: >=3.8
License-File: LICENSE.rst
Requires-Dist: matplotlib
Requires-Dist: pytest
Provides-Extra: all
Requires-Dist: nbsphinx >=0.6.0 ; extra == 'all'
Requires-Dist: nengo-sphinx-theme >1.2.2 ; extra == 'all'
Requires-Dist: numpydoc >=0.9.2 ; extra == 'all'
Requires-Dist: sphinx ; extra == 'all'
Requires-Dist: pytest-cov ; extra == 'all'
Provides-Extra: docs
Requires-Dist: nbsphinx >=0.6.0 ; extra == 'docs'
Requires-Dist: nengo-sphinx-theme >1.2.2 ; extra == 'docs'
Requires-Dist: numpydoc >=0.9.2 ; extra == 'docs'
Requires-Dist: sphinx ; extra == 'docs'
Provides-Extra: optional
Provides-Extra: tests
Requires-Dist: pytest-cov ; extra == 'tests'
